skippy/__init__.py
skippy/__main__.py
skippy/classification.py
skippy/get_data.py
skippy/get_model.py
skippy/pickle_model.py
skippy/plot.py
skippy/regression.py
skippy/split_data.py
skippy-0.1.0.dist-info/METADATA
skippy-0.1.0.dist-info/RECORD
skippy-0.1.0.dist-info/WHEEL
skippy-0.1.0.dist-info/entry_points.txt
skippy-0.1.0.dist-info/top_level.txt
