Metadata-Version: 2.1
Name: skippy
Version: 0.1.0
Summary: Simplified analysis of sklearn datasets
Home-page: https://github.com/marskar/skippy
Author: Martin Skarzynski
Author-email: marskar@gmail.com
License: UNKNOWN
Platform: UNKNOWN
Classifier: Programming Language :: Python :: 3
Classifier: License :: OSI Approved :: MIT License
Classifier: Operating System :: OS Independent
Requires-Dist: scikit-learn
Requires-Dist: matplotlib
Requires-Dist: seaborn
